vltava/__init__.py
vltava/resources/__init__.py
vltava/resources/cs.stopwords
vltava/resources/majka.w-lt
vltava/resources/nlp_czech-morfflex-161115-no_dia.dict
vltava-0.1.3.dist-info/LICENSE
vltava-0.1.3.dist-info/METADATA
vltava-0.1.3.dist-info/WHEEL
vltava-0.1.3.dist-info/top_level.txt
vltava-0.1.3.dist-info/RECORD
